<annotation>
	<folder>200</folder>
	<filename>20210324_193306.jpg</filename>
	<path>/home/superdiodo/University/APMS/Euro_coin_dataset/images_take_good/200/20210324_193306.jpg</path>
	<source>
		<database>Unknown</database>
	</source>
	<size>
		<width>3024</width>
		<height>3024</height>
		<depth>3</depth>
	</size>
	<segmented>0</segmented>
	<object>
		<name>200</name>
		<pose>Unspecified</pose>
		<truncated>0</truncated>
		<difficult>0</difficult>
		<bndbox>
			<xmin>393</xmin>
			<ymin>577</ymin>
			<xmax>856</xmax>
			<ymax>1037</ymax>
		</bndbox>
	</object>
	<object>
		<name>200</name>
		<pose>Unspecified</pose>
		<truncated>0</truncated>
		<difficult>0</difficult>
		<bndbox>
			<xmin>1187</xmin>
			<ymin>652</ymin>
			<xmax>1628</xmax>
			<ymax>1099</ymax>
		</bndbox>
	</object>
	<object>
		<name>200</name>
		<pose>Unspecified</pose>
		<truncated>0</truncated>
		<difficult>0</difficult>
		<bndbox>
			<xmin>1884</xmin>
			<ymin>702</ymin>
			<xmax>2318</xmax>
			<ymax>1184</ymax>
		</bndbox>
	</object>
	<object>
		<name>200</name>
		<pose>Unspecified</pose>
		<truncated>0</truncated>
		<difficult>0</difficult>
		<bndbox>
			<xmin>421</xmin>
			<ymin>1481</ymin>
			<xmax>890</xmax>
			<ymax>1946</ymax>
		</bndbox>
	</object>
	<object>
		<name>200</name>
		<pose>Unspecified</pose>
		<truncated>0</truncated>
		<difficult>0</difficult>
		<bndbox>
			<xmin>1131</xmin>
			<ymin>1493</ymin>
			<xmax>1584</xmax>
			<ymax>1940</ymax>
		</bndbox>
	</object>
	<object>
		<name>200</name>
		<pose>Unspecified</pose>
		<truncated>0</truncated>
		<difficult>0</difficult>
		<bndbox>
			<xmin>1884</xmin>
			<ymin>1568</ymin>
			<xmax>2371</xmax>
			<ymax>2021</ymax>
		</bndbox>
	</object>
</annotation>
