<annotation>
	<folder>mixed</folder>
	<filename>20210327_181139.jpg</filename>
	<path>/home/superdiodo/University/APMS/euro-coin-dataset/mixed/20210327_181139.jpg</path>
	<source>
		<database>Unknown</database>
	</source>
	<size>
		<width>3024</width>
		<height>3024</height>
		<depth>3</depth>
	</size>
	<segmented>0</segmented>
	<object>
		<name>100</name>
		<pose>Unspecified</pose>
		<truncated>0</truncated>
		<difficult>0</difficult>
		<bndbox>
			<xmin>215</xmin>
			<ymin>793</ymin>
			<xmax>996</xmax>
			<ymax>1581</ymax>
		</bndbox>
	</object>
	<object>
		<name>100</name>
		<pose>Unspecified</pose>
		<truncated>0</truncated>
		<difficult>0</difficult>
		<bndbox>
			<xmin>1093</xmin>
			<ymin>777</ymin>
			<xmax>1912</xmax>
			<ymax>1599</ymax>
		</bndbox>
	</object>
	<object>
		<name>100</name>
		<pose>Unspecified</pose>
		<truncated>0</truncated>
		<difficult>0</difficult>
		<bndbox>
			<xmin>2049</xmin>
			<ymin>902</ymin>
			<xmax>2837</xmax>
			<ymax>1718</ymax>
		</bndbox>
	</object>
	<object>
		<name>100</name>
		<pose>Unspecified</pose>
		<truncated>0</truncated>
		<difficult>0</difficult>
		<bndbox>
			<xmin>521</xmin>
			<ymin>1534</ymin>
			<xmax>1318</xmax>
			<ymax>2362</ymax>
		</bndbox>
	</object>
	<object>
		<name>100</name>
		<pose>Unspecified</pose>
		<truncated>0</truncated>
		<difficult>0</difficult>
		<bndbox>
			<xmin>1481</xmin>
			<ymin>1790</ymin>
			<xmax>2315</xmax>
			<ymax>2606</ymax>
		</bndbox>
	</object>
</annotation>
